pluck/__init__.py
pluck/_decorators.py
pluck/_execution.py
pluck/_json.py
pluck/_libraries.py
pluck/_normalization.py
pluck/_parser.py
pluck/_pluck.py
pluck/client.py
pluck_graphql-0.4.0.dist-info/LICENSE
pluck_graphql-0.4.0.dist-info/METADATA
pluck_graphql-0.4.0.dist-info/WHEEL
pluck_graphql-0.4.0.dist-info/RECORD
